improve_prompt/__init__.py
improve_prompt/improve_prompt.py
improve_prompt-0.1.0.dist-info/licenses/LICENSE
improve_prompt-0.1.0.dist-info/METADATA
improve_prompt-0.1.0.dist-info/WHEEL
improve_prompt-0.1.0.dist-info/entry_points.txt
improve_prompt-0.1.0.dist-info/top_level.txt
improve_prompt-0.1.0.dist-info/RECORD
